qcoptimizer/__init__.py
qcoptimizer/data/PerthSimRegModel.sav
qcoptimizer-0.0.2.7.dist-info/LICENSE
qcoptimizer-0.0.2.7.dist-info/METADATA
qcoptimizer-0.0.2.7.dist-info/WHEEL
qcoptimizer-0.0.2.7.dist-info/top_level.txt
qcoptimizer-0.0.2.7.dist-info/RECORD
