Metadata-Version: 2.1
Name: qcoptimizer
Version: 0.0.2.7
Summary: A package for quantum circuit complexity-based optimization through Qiskit optimization level assignment
Home-page: UNKNOWN
Author: Taren Patel
Author-email: tarenpatel1013@gmail.com
License: UNKNOWN
Platform: UNKNOWN
Classifier: Programming Language :: Python :: 3
Classifier: License :: OSI Approved :: MIT License
Classifier: Operating System :: OS Independent
Requires-Python: >=3.7
